{"chunk_definitions":[{"row":92,"row_count":1,"visible":true,"expansion_state":0,"options":{"engine":"r","label":"unnamed-chunk-35","dev":"png"},"document_id":"CBA2A897","chunk_id":"czspncf278r7w","chunk_label":""},{"row":103,"row_count":1,"visible":true,"expansion_state":0,"options":{"engine":"r","label":"unnamed-chunk-36","dev":"png"},"document_id":"CBA2A897","chunk_id":"czepml2t5skrl","chunk_label":""},{"row":134,"row_count":1,"visible":true,"expansion_state":0,"options":{"engine":"r","label":"unnamed-chunk-42","dev":"png"},"document_id":"CBA2A897","chunk_id":"c1n7g08sz3o1c","chunk_label":""},{"row":141,"row_count":1,"visible":true,"expansion_state":0,"options":{"engine":"r","label":"unnamed-chunk-44","dev":"png"},"document_id":"CBA2A897","chunk_id":"ceojzk9wqe5t5","chunk_label":"unnamed-chunk-11"},{"row":150,"row_count":1,"visible":true,"expansion_state":0,"options":{"engine":"r","label":"unnamed-chunk-47","dev":"png"},"document_id":"CBA2A897","chunk_id":"cw1zjhzr3v6n7","chunk_label":"unnamed-chunk-12"},{"row":158,"row_count":1,"visible":true,"expansion_state":0,"options":{"engine":"r","label":"unnamed-chunk-48","dev":"png"},"document_id":"CBA2A897","chunk_id":"cfe61y67e948r","chunk_label":"unnamed-chunk-13"},{"row":180,"row_count":1,"visible":true,"expansion_state":0,"options":{"engine":"r","label":"unnamed-chunk-52","dev":"png"},"document_id":"CBA2A897","chunk_id":"chryelumz2wmi","chunk_label":"unnamed-chunk-15"},{"row":188,"row_count":1,"visible":true,"expansion_state":0,"options":{"engine":"r","label":"unnamed-chunk-53","dev":"png"},"document_id":"CBA2A897","chunk_id":"cdg40bszs3z7d","chunk_label":"unnamed-chunk-16"},{"row":227,"row_count":1,"visible":true,"expansion_state":0,"options":{"engine":"r","label":"unnamed-chunk-49","dev":"png"},"document_id":"CBA2A897","chunk_id":"c2otakbnna2hn","chunk_label":"unnamed-chunk-19"},{"row":238,"row_count":1,"visible":true,"expansion_state":0,"options":{"engine":"r","label":"unnamed-chunk-50","dev":"png"},"document_id":"CBA2A897","chunk_id":"cfq85gdsm9ge2","chunk_label":""},{"row":284,"row_count":1,"visible":true,"expansion_state":0,"options":{"engine":"r","label":"unnamed-chunk-56","dev":"png"},"document_id":"CBA2A897","chunk_id":"c4le79msqk01g","chunk_label":"unnamed-chunk-23"},{"row":301,"row_count":1,"visible":true,"expansion_state":0,"options":{"engine":"r","label":"unnamed-chunk-57","dev":"png"},"document_id":"CBA2A897","chunk_id":"clxqzbf61xk2x","chunk_label":""},{"row":325,"row_count":1,"visible":true,"expansion_state":0,"options":{"engine":"r","label":"unnamed-chunk-58","dev":"png"},"document_id":"CBA2A897","chunk_id":"cb6cxkz3j7g7t","chunk_label":"unnamed-chunk-26"},{"row":368,"row_count":1,"visible":true,"expansion_state":0,"options":{"engine":"r","label":"unnamed-chunk-61","dev":"png"},"document_id":"CBA2A897","chunk_id":"c3s3kxgk31eye","chunk_label":""}],"doc_write_time":1748984133}